bcp_in/__init__.py
bcp_in/bcp_utils.py
bcp_in-0.1.dist-info/METADATA
bcp_in-0.1.dist-info/WHEEL
bcp_in-0.1.dist-info/top_level.txt
bcp_in-0.1.dist-info/RECORD
