Metadata-Version: 2.1
Name: bcp-in
Version: 0.1
Summary: A simple wrapper around the bcp utility, focused on inserting data to the SQL Server db
Home-page: https://github.com/inabeo/bcp_in
Author: inabeo
License: UNKNOWN
Platform: UNKNOWN
